simplestretch/__init__.py
simplestretch/cli.py
simpleaudiostretch-0.2.4.dist-info/METADATA
simpleaudiostretch-0.2.4.dist-info/WHEEL
simpleaudiostretch-0.2.4.dist-info/entry_points.txt
simpleaudiostretch-0.2.4.dist-info/licenses/LICENSE
simpleaudiostretch-0.2.4.dist-info/RECORD
