Metadata-Version: 2.3
Name: simpleaudiostretch
Version: 0.2.4
Summary: A small package to stretch audio
Project-URL: Homepage, https://github.com/Mews/simpleaudiostretch
Project-URL: Issues, https://github.com/Mews/simpleaudiostretch/issues
Author-email: Mews <tiraraspas@gmail.com>
License-File: LICENSE
Keywords: audio,mp3,sound,speed,stretch,wav
Classifier: License :: OSI Approved :: GNU General Public License v3 (GPLv3)
Classifier: Operating System :: OS Independent
Classifier: Programming Language :: Python :: 3
Requires-Python: >=3.8
Requires-Dist: numpy
Requires-Dist: soundfile
